edb_obs_ws/__init__.py
edb_obs_ws/endpoints.py
edb_obs_ws/event.py
el_decko_backend_obs_ws-2023.5.3.dist-info/LICENSE
el_decko_backend_obs_ws-2023.5.3.dist-info/METADATA
el_decko_backend_obs_ws-2023.5.3.dist-info/WHEEL
el_decko_backend_obs_ws-2023.5.3.dist-info/entry_points.txt
el_decko_backend_obs_ws-2023.5.3.dist-info/top_level.txt
el_decko_backend_obs_ws-2023.5.3.dist-info/RECORD
