Metadata-Version: 2.1
Name: el-decko-backend-obs-ws
Version: 2023.5.3
Summary: OBS Studio websocket backend for El Decko. Allow your Elgato Stream Deck to control OBS Studio using it's webscoket server
Author-email: Imo 'Vortex Acherontic' Hester <vortex@z-ray.de>
License: GPL-3
Project-URL: Homepage, https://github.com/Z-Ray-Entertainment/el_decko_backend_obs_ws
Project-URL: Bug Tracker, https://github.com/Z-Ray-Entertainment/el_decko_backend_obs_ws/issues
Platform: Linux
Requires-Python: >=3.8
License-File: LICENSE
Requires-Dist: simpleobsws
Requires-Dist: xdg
